LICENSE
README.md
setup.py
pyPman/__init__.py
pyPman/__main__.py
pyPman.egg-info/PKG-INFO
pyPman.egg-info/SOURCES.txt
pyPman.egg-info/dependency_links.txt
pyPman.egg-info/entry_points.txt
pyPman.egg-info/requires.txt
pyPman.egg-info/top_level.txt
pyPman/initialize/__init__.py
pyPman/initialize/projectInitialize.py
pyPman/install/__init__.py
pyPman/install/builder.py
pyPman/install/init_builder.py
pyPman/install/license_builder.py
pyPman/install/main_builder.py
pyPman/install/readme_builder.py
pyPman/install/setup_builder.py
pyPman/install/utils.py
pyPman/utilities/__init__.py
pyPman/utilities/moduleVersion.py
pyPman/utilities/utils.py